LICENSE
MANIFEST.in
README.md
pyproject.toml
setup.cfg
setup.py
src/uavdex/__init__.py
src/uavdex/common.py
src/uavdex/localtests.py
src/uavdex/module1.py
src/uavdex/performance.py
src/uavdex/propulsions.py
src/uavdex.egg-info/PKG-INFO
src/uavdex.egg-info/SOURCES.txt
src/uavdex.egg-info/dependency_links.txt
src/uavdex.egg-info/requires.txt
src/uavdex.egg-info/top_level.txt
src/uavdex/Databases/Batteries.csv
src/uavdex/Databases/ESCs_Gong.csv
src/uavdex/Databases/ESCs_Saemi.csv
src/uavdex/Databases/MotorCurveFits.xlsx
src/uavdex/Databases/Motors.csv
src/uavdex/Databases/APCPropDatabase/PER3_105x45.dat
src/uavdex/Databases/APCPropDatabase/PER3_105x6.dat
src/uavdex/Databases/APCPropDatabase/PER3_10x10.dat
src/uavdex/Databases/APCPropDatabase/PER3_10x10E.dat
src/uavdex/Databases/APCPropDatabase/PER3_10x12WE.dat
src/uavdex/Databases/APCPropDatabase/PER3_10x3.dat
src/uavdex/Databases/APCPropDatabase/PER3_10x38MRF-RH.dat
src/uavdex/Databases/APCPropDatabase/PER3_10x38SF.dat
src/uavdex/Databases/APCPropDatabase/PER3_10x4.dat
src/uavdex/Databases/APCPropDatabase/PER3_10x45MR.dat
src/uavdex/Databases/APCPropDatabase/PER3_10x45MRF-RH.dat
src/uavdex/Databases/APCPropDatabase/PER3_10x46SF.dat
src/uavdex/Databases/APCPropDatabase/PER3_10x47SF.dat
src/uavdex/Databases/APCPropDatabase/PER3_10x5.dat
src/uavdex/Databases/APCPropDatabase/PER3_10x55MR.dat
src/uavdex/Databases/APCPropDatabase/PER3_10x58EP(F2B).dat
src/uavdex/Databases/APCPropDatabase/PER3_10x5E.dat
src/uavdex/Databases/APCPropDatabase/PER3_10x6-4.dat
src/uavdex/Databases/APCPropDatabase/PER3_10x6.dat
src/uavdex/Databases/APCPropDatabase/PER3_10x6E.dat
src/uavdex/Databases/APCPropDatabase/PER3_10x6F.dat
src/uavdex/Databases/APCPropDatabase/PER3_10x7.dat
src/uavdex/Databases/APCPropDatabase/PER3_10x7E.dat
src/uavdex/Databases/APCPropDatabase/PER3_10x7SF.dat
src/uavdex/Databases/APCPropDatabase/PER3_10x8.dat
src/uavdex/Databases/APCPropDatabase/PER3_10x8E.dat
src/uavdex/Databases/APCPropDatabase/PER3_10x9.dat
src/uavdex/Databases/APCPropDatabase/PER3_115x4.dat
src/uavdex/Databases/APCPropDatabase/PER3_115x6.dat
src/uavdex/Databases/APCPropDatabase/PER3_11x10.dat
