Metadata-Version: 2.4
Name: uavdex
Version: 0.1.2
Summary: Unmanned Aerial Vehicle Design EXploration.
Home-page: https://github.com/sammy183/UAVDEX
Author: Samuel Nassau
Author-email: Samuel Noble Nassau <sammynassau@gmail.com>
License-Expression: MIT
Classifier: Programming Language :: Python :: 3
Classifier: Operating System :: OS Independent
Requires-Python: >=3.9
License-File: LICENSE
Requires-Dist: matplotlib
Requires-Dist: numpy
Requires-Dist: scipy
Requires-Dist: gekko
Requires-Dist: pandas
Requires-Dist: tqdm
Dynamic: author
Dynamic: home-page
Dynamic: license-file
Dynamic: requires-python
